spmo/__init__.py
spmo/common.py
spmo/data_serialize.py
spmo/settings.py
spmo/conf/effective_tld_names.dat
spmo/conf/whois.servers.json
spmo/datetime_s/__init__.py
spmo/datetime_s/common.py
spmo/db/__init__.py
spmo/db/common.py
spmo/db/mysql.py
spmo/file/__init__.py
spmo/file/common.py
spmo/net/__init__.py
spmo/net/domain.py
spmo/net/http.py
spmo/net/network.py
spmo/strings/__init__.py
spmo/strings/common.py
spmo-2.0.9.dist-info/LICENSE.txt
spmo-2.0.9.dist-info/METADATA
spmo-2.0.9.dist-info/WHEEL
spmo-2.0.9.dist-info/top_level.txt
spmo-2.0.9.dist-info/RECORD
