Metadata-Version: 2.1
Name: spmo
Version: 2.0.9
Summary: SPMO collect some userful python Class And Function
Home-page: https://github.com/spunkmars/spmo
Author: SpunkMars++
Author-email: spunkmars@gmail.com
License: BSD
Keywords: spmo setuptools development
Platform: UNKNOWN
Classifier: Development Status :: 5 - Production/Stable
Classifier: Intended Audience :: Developers
Classifier: Topic :: Software Development :: Build Tools
Classifier: License :: OSI Approved :: BSD License
Classifier: Programming Language :: Python :: 2
Classifier: Programming Language :: Python :: 2.6
Classifier: Programming Language :: Python :: 2.7
Classifier: Programming Language :: Python :: 3
Classifier: Programming Language :: Python :: 3.3
Classifier: Programming Language :: Python :: 3.4
Classifier: Programming Language :: Python :: 3.5
Classifier: Programming Language :: Python :: 3.6
